{
  "name": "Prisonnier",
  "type": "inconvenient",
  "img": "systems/knight/assets/icons/inconvenient.svg",
  "system": {
    "description": "<p>L'IA désire par-dessus tout devenir complète et, pour cela, elle a besoin que son autre, le chevalier, s'unisse à elle définitivement. Elle ne se folde jamais, sauf si d'un commun accord le chevalier et la machine estiment que la situation impose que l'armure soit foldée. Mais dès cette situation passée, l'armure se remet en place automatiquement. En termes de jeu, le joueur ne peut pas folder comme il le souhaite.</p>\n",
    "type": "ia",
    "limitations": {
      "aspects": {
        "all": {
          "has": false,
          "value": 9
        },
        "bete": {
          "has": false,
          "value": 9,
          "max": 9
        },
        "chair": {
          "has": false,
          "value": 9,
          "max": 9
        },
        "machine": {
          "has": false,
          "value": 9,
          "max": 9
        },
        "dame": {
          "has": false,
          "value": 9,
          "max": 9
        },
        "masque": {
          "has": false,
          "value": 9,
          "max": 9
        }
      },
      "espoir": {
        "aucunGain": false
      }
    },
    "malus": {
      "sante": 0,
      "espoir": 0,
      "initiative": {
        "dice": 0,
        "fixe": 0,
        "ifEmbuscade": {
          "has": false,
          "dice": 0,
          "fixe": 0
        }
      },
      "recuperation": {
        "sante": 0,
        "armure": 0,
        "energie": 0,
        "espoir": 0
      },
      "coutsAugmentes": {
        "has": false,
        "aspect": {
          "multiplie": 0,
          "value": 0
        },
        "caracteristique": {
          "multiplie": 0,
          "value": 0
        }
      }
    }
  },
  "effects": [],
  "_id": "3ff95bd8963c86e6",
  "folder": null,
  "sort": 0,
  "ownership": {
    "default": 0
  },
  "flags": {
    "core": {
      "sourceId": "Compendium.knight-compendium.ai-disadvantages-base.3ff95bd8963c86e6"
    }
  },
  "_stats": {
    "systemId": "knight",
    "systemVersion": "1.8.6",
    "coreVersion": "10.288",
    "createdTime": 1668025962893,
    "modifiedTime": 1668026687803,
    "lastModifiedBy": "Kisv9JwB5w6zIXyv"
  },
  "_key": "!items!3ff95bd8963c86e6"
}
