{
  "name": "Citoyen de l'arche Oslo-Asgard",
  "type": "bande",
  "img": "systems/knight/assets/icons/bande.svg",
  "system": {
    "combat": {
      "armesimprovisees": {
        "aspect": "chair",
        "contact": "combat",
        "distance": "tir",
        "liste": {
          "ai1": {
            "force": 1,
            "chair": [
              1,
              2
            ],
            "liste": {
              "1": {
                "degats": {
                  "dice": 4
                },
                "violence": {
                  "dice": 4
                },
                "effets": {
                  "raw": [],
                  "custom": []
                },
                "utilisations": 3
              },
              "2": {
                "force": 1,
                "chair": [
                  1,
                  2
                ],
                "degats": {
                  "dice": 2
                },
                "violence": {
                  "dice": 5
                },
                "effets": {
                  "raw": [],
                  "custom": []
                },
                "utilisations": 1
              },
              "3": {
                "force": 1,
                "chair": [
                  1,
                  2
                ],
                "degats": {
                  "dice": 4
                },
                "violence": {
                  "dice": 4
                },
                "effets": {
                  "raw": [],
                  "custom": []
                },
                "utilisations": 2
              }
            }
          },
          "ai2": {
            "force": 2,
            "chair": [
              3,
              4
            ],
            "liste": {
              "1": {
                "degats": {
                  "dice": 6
                },
                "violence": {
                  "dice": 4
                },
                "effets": {
                  "raw": [],
                  "custom": []
                },
                "utilisations": 3
              },
              "2": {
                "degats": {
                  "dice": 4
                },
                "violence": {
                  "dice": 6
                },
                "effets": {
                  "raw": [],
                  "custom": []
                },
                "utilisations": 1
              },
              "3": {
                "degats": {
                  "dice": 5
                },
                "violence": {
                  "dice": 5
                },
                "effets": {
                  "raw": [],
                  "custom": []
                },
                "utilisations": 2
              }
            }
          },
          "ai3": {
            "force": 3,
            "chair": [
              5,
              6
            ],
            "liste": {
              "1": {
                "degats": {
                  "dice": 7
                },
                "violence": {
                  "dice": 5
                },
                "effets": {
                  "raw": [],
                  "custom": []
                },
                "utilisations": 3
              },
              "2": {
                "degats": {
                  "dice": 5
                },
                "violence": {
                  "dice": 7
                },
                "effets": {
                  "raw": [],
                  "custom": []
                },
                "utilisations": 1
              },
              "3": {
                "degats": {
                  "dice": 6
                },
                "violence": {
                  "dice": 6
                },
                "effets": {
                  "raw": [],
                  "custom": []
                },
                "utilisations": 2
              }
            }
          },
          "ai4": {
            "force": 4,
            "chair": [
              7,
              8
            ],
            "liste": {
              "1": {
                "degats": {
                  "dice": 7
                },
                "violence": {
                  "dice": 9
                },
                "effets": {
                  "raw": [],
                  "custom": []
                },
                "utilisations": 1
              },
              "2": {
                "degats": {
                  "dice": 8
                },
                "violence": {
                  "dice": 8
                },
                "effets": {
                  "raw": [],
                  "custom": []
                },
                "utilisations": 2
              }
            }
          },
          "ai5": {
            "force": 5,
            "chair": [
              9,
              10
            ],
            "liste": {
              "1": {
                "degats": {
                  "dice": 10
                },
                "violence": {
                  "dice": 12
                },
                "effets": {
                  "raw": [],
                  "custom": []
                },
                "utilisations": 1
              },
              "2": {
                "degats": {
                  "dice": 11
                },
                "violence": {
                  "dice": 11
                },
                "effets": {
                  "raw": [],
                  "custom": []
                },
                "utilisations": 2
              }
            }
          }
        }
      },
      "data": {
        "modificateur": 0,
        "succesbonus": 0,
        "degatsbonus": {
          "dice": 0,
          "fixe": 0
        },
        "violencebonus": {
          "dice": 0,
          "fixe": 0
        }
      }
    },
    "aspects": {
      "chair": {
        "value": 10,
        "max": 20,
        "ae": {
          "mineur": {
            "value": "2",
            "max": 10
          },
          "majeur": {
            "value": "0",
            "max": 10
          }
        }
      },
      "bete": {
        "value": 12,
        "max": 20,
        "ae": {
          "mineur": {
            "value": "2",
            "max": 10
          },
          "majeur": {
            "value": "0",
            "max": 10
          }
        }
      },
      "machine": {
        "value": 4,
        "max": 20,
        "ae": {
          "mineur": {
            "value": "0",
            "max": 10
          },
          "majeur": {
            "value": "0",
            "max": 10
          }
        }
      },
      "dame": {
        "value": 4,
        "max": 20,
        "ae": {
          "mineur": {
            "value": "0",
            "max": 10
          },
          "majeur": {
            "value": "0",
            "max": 10
          }
        }
      },
      "masque": {
        "value": 6,
        "max": 20,
        "ae": {
          "mineur": {
            "value": "0",
            "max": 10
          },
          "majeur": {
            "value": "0",
            "max": 10
          }
        }
      }
    },
    "initiative": {
      "dice": 3,
      "value": 0,
      "diceBase": 3,
      "diceBonus": {},
      "diceMalus": {},
      "bonus": {
        "user": 0
      },
      "malus": {
        "user": 0
      },
      "embuscade": {
        "diceBonus": {},
        "diceMalus": {},
        "bonus": {},
        "malus": {}
      }
    },
    "reaction": {
      "bonus": {
        "user": 0,
        "armes": 0,
        "capacites": 0
      },
      "malus": {
        "user": 0,
        "capacites": 0,
        "armes": 0
      },
      "bonusValue": 0,
      "malusValue": 0,
      "value": 0,
      "base": 3,
      "optionDeploy": false
    },
    "defense": {
      "bonus": {
        "user": 0,
        "armes": 0,
        "capacites": 0
      },
      "malus": {
        "user": 0,
        "capacites": 0,
        "armes": 0
      },
      "bonusValue": 0,
      "malusValue": 0,
      "value": 0,
      "base": 3,
      "optionDeploy": false
    },
    "sante": {
      "bonus": {
        "user": 0,
        "capacites": 0
      },
      "malus": {
        "user": 0,
        "capacites": 0
      },
      "bonusValue": 0,
      "malusValue": 0,
      "value": 0,
      "max": 0,
      "base": 300,
      "optionDeploy": false
    },
    "description": "<p>Les m&eacute;ta-soldats du Nodachi forment le gros des troupes de combat. Chacun d&rsquo;entre eux est &eacute;quip&eacute; d&rsquo;un exosquelette de type Kirin qui le dote d&rsquo;une meilleure puissance physique et de possibilit&eacute;s de saut impressionnantes. Regroup&eacute;s en escouades d&rsquo;une demi-douzaine d&rsquo;hommes, ils sont &eacute;quip&eacute;s de trois petits drones polymorphes de type Obake et d&rsquo;armes diverses comme le fusil d&rsquo;assaut Askr-1 ou la mitrailleuse Onagre.</p>",
    "histoire": "",
    "phase2Activate": false,
    "phase2": {
      "sante": 0,
      "aspects": {
        "chair": {
          "value": 0,
          "ae": {
            "mineur": 0,
            "majeur": 0
          }
        },
        "bete": {
          "value": 0,
          "ae": {
            "mineur": 0,
            "majeur": 0
          }
        },
        "machine": {
          "value": 0,
          "ae": {
            "mineur": 0,
            "majeur": 0
          }
        },
        "dame": {
          "value": 0,
          "ae": {
            "mineur": 0,
            "majeur": 0
          }
        },
        "masque": {
          "value": 0,
          "ae": {
            "mineur": 0,
            "majeur": 0
          }
        }
      }
    },
    "debordement": {
      "value": 10,
      "tour": 1
    },
    "energie": {
      "value": 0,
      "max": 0
    },
    "bouclier": {
      "value": 0,
      "max": 0,
      "base": 6,
      "bonus": {
        "user": 0
      },
      "malus": {
        "user": 0
      },
      "optionDeploy": false
    },
    "options": {
      "bouclier": true
    },
    "armure": {
      "bonus": {
        "modules": 0,
        "capacites": 0
      }
    },
    "type": "Bande (héros)",
    "tactique": "<p>Les m&eacute;ta-soldats agissent en escouades de combat se concentrant chacune sur une menace. Ils sont en g&eacute;n&eacute;ral dirig&eacute;s par des yojimbos et des samoura&iuml;s. Si tous leurs meneurs d&rsquo;hommes sont morts et que leur coh&eacute;sion a baiss&eacute; de la moiti&eacute;, ils se rendent.</p>"
  },
  "prototypeToken": {
    "name": "Méta-soldat",
    "displayName": 0,
    "actorLink": false,
    "texture": {
      "src": "systems/knight/assets/icons/bande.svg",
      "scaleX": 1,
      "scaleY": 1,
      "offsetX": 0,
      "offsetY": 0,
      "rotation": 0,
      "tint": null
    },
    "width": 1,
    "height": 1,
    "lockRotation": false,
    "rotation": 0,
    "alpha": 1,
    "disposition": -1,
    "displayBars": 0,
    "bar1": {
      "attribute": null
    },
    "bar2": {
      "attribute": null
    },
    "light": {
      "alpha": 0.5,
      "angle": 360,
      "bright": 0,
      "color": null,
      "coloration": 1,
      "dim": 0,
      "attenuation": 0.5,
      "luminosity": 0.5,
      "saturation": 0,
      "contrast": 0,
      "shadows": 0,
      "animation": {
        "type": null,
        "speed": 5,
        "intensity": 5,
        "reverse": false
      },
      "darkness": {
        "min": 0,
        "max": 1
      }
    },
    "sight": {
      "enabled": false,
      "range": null,
      "angle": 360,
      "visionMode": "basic",
      "color": null,
      "attenuation": 0.1,
      "brightness": 0,
      "saturation": 0,
      "contrast": 0
    },
    "detectionModes": [],
    "flags": {},
    "randomImg": false
  },
  "items": [
    {
      "name": "Exosquelette de combat (nv1)",
      "type": "capacite",
      "img": "systems/knight/assets/icons/capacite.svg",
      "system": {
        "description": "<p>Le PNJ bénéficie d'aspects exceptionnels et d'un module de saut et de course nvX. Si ses PA tombent à 0, ces bénéfices sont annulés.</p>\n",
        "aspects": {
          "chair": {},
          "bete": {},
          "machine": {},
          "dame": {},
          "masque": {}
        },
        "isPhase2": false,
        "bonus": {
          "aspectsLieSupplementaire": {
            "has": false,
            "value": "chair"
          },
          "sante": {
            "has": false,
            "aspect": {
              "lie": false,
              "value": "chair",
              "multiplie": 5
            },
            "value": 0
          },
          "armure": {
            "has": false,
            "aspect": {
              "lie": false,
              "value": "chair",
              "multiplie": 5
            },
            "value": 0
          },
          "aspectMax": {
            "has": false,
            "aspect": "chair",
            "maximum": {
              "aspect": 40,
              "ae": 20
            }
          }
        },
        "degats": {
          "has": false,
          "system": {
            "dice": 0,
            "fixe": 0,
            "effets": {
              "raw": [],
              "custom": [],
              "liste": []
            }
          }
        },
        "attaque": {
          "has": false,
          "type": "contact",
          "portee": "contact",
          "degats": {
            "dice": 0,
            "fixe": 0
          },
          "effets": {
            "raw": [],
            "custom": [],
            "liste": []
          }
        },
        "phase2": {
          "aspects": {
            "has": false,
            "liste": {
              "chair": {
                "value": 0
              },
              "bete": {
                "value": 0
              },
              "machine": {
                "value": 0
              },
              "dame": {
                "value": 0
              },
              "masque": {
                "value": 0
              }
            }
          },
          "sante": {
            "has": false,
            "value": 0
          },
          "armure": {
            "has": false,
            "value": 0
          },
          "tactique": {
            "has": false,
            "value": ""
          }
        }
      },
      "effects": [],
      "_id": "lQ8thiBv01ZaEgkY",
      "ownership": {
        "default": 0
      },
      "flags": {
        "core": {
          "sourceId": "Compendium.knight-compendium.npc-capacities-base.82424419a75bed1f"
        }
      },
      "_stats": {
        "systemId": "knight",
        "systemVersion": "1.4.9",
        "coreVersion": "10.288",
        "createdTime": 1666890018902,
        "modifiedTime": 1667212990571,
        "lastModifiedBy": "y7bwecrKsFInhWQ1"
      },
      "folder": "FdIw3AaAAqfstH0n",
      "sort": 0,
      "_key": "!actors.items!Q1Jo0bLeYPUEFL1G.lQ8thiBv01ZaEgkY"
    },
    {
      "name": "Drones Obake",
      "type": "capacite",
      "img": "systems/knight/assets/icons/capacite.svg",
      "system": {
        "description": "<p>Trois fois durant le combat et une seule fois par tour, les drones peuvent faire feu pour protéger les PNJ. Les PJ sont automatiquement touchés et subissent 5D6 + 10 points de dégâts (un jet séparé pour chaque PJ).</p>\n",
        "aspects": {
          "chair": {},
          "bete": {},
          "machine": {},
          "dame": {},
          "masque": {}
        },
        "isPhase2": false,
        "bonus": {
          "aspectsLieSupplementaire": {
            "has": false,
            "value": "chair"
          },
          "sante": {
            "has": false,
            "aspect": {
              "lie": false,
              "value": "chair",
              "multiplie": 5
            },
            "value": 0
          },
          "armure": {
            "has": false,
            "aspect": {
              "lie": false,
              "value": "chair",
              "multiplie": 5
            },
            "value": 0
          },
          "aspectMax": {
            "has": false,
            "aspect": "chair",
            "maximum": {
              "aspect": 40,
              "ae": 20
            }
          }
        },
        "degats": {
          "has": false,
          "system": {
            "dice": 0,
            "fixe": 0,
            "effets": {
              "raw": [],
              "custom": [],
              "liste": []
            }
          }
        },
        "attaque": {
          "has": false,
          "type": "contact",
          "portee": "contact",
          "degats": {
            "dice": 0,
            "fixe": 0
          },
          "effets": {
            "raw": [],
            "custom": [],
            "liste": []
          }
        },
        "phase2": {
          "aspects": {
            "has": false,
            "liste": {
              "chair": {
                "value": 0
              },
              "bete": {
                "value": 0
              },
              "machine": {
                "value": 0
              },
              "dame": {
                "value": 0
              },
              "masque": {
                "value": 0
              }
            }
          },
          "sante": {
            "has": false,
            "value": 0
          },
          "armure": {
            "has": false,
            "value": 0
          },
          "tactique": {
            "has": false,
            "value": ""
          }
        }
      },
      "effects": [],
      "_id": "JctxqeYkGJB25n7d",
      "ownership": {
        "default": 0
      },
      "flags": {
        "core": {
          "sourceId": "Compendium.knight-compendium.npc-capacities-base.fefe1d802926e0fc"
        }
      },
      "_stats": {
        "systemId": "knight",
        "systemVersion": "1.4.9",
        "coreVersion": "10.288",
        "createdTime": 1666890019312,
        "modifiedTime": 1667213001374,
        "lastModifiedBy": "y7bwecrKsFInhWQ1"
      },
      "folder": "FdIw3AaAAqfstH0n",
      "sort": 0,
      "_key": "!actors.items!Q1Jo0bLeYPUEFL1G.JctxqeYkGJB25n7d"
    },
    {
      "name": "Désespérant",
      "type": "capacite",
      "img": "systems/knight/assets/icons/capacite.svg",
      "system": {
        "description": "<p>Si un PJ détruit le PNJ, il doit réussir un test base Hargne combo Sang-Froid (difficulté au choix du MJ) pour ne pas perdre 1D6 point d'espoir.</p>\n",
        "aspects": {
          "chair": {},
          "bete": {},
          "machine": {},
          "dame": {},
          "masque": {}
        },
        "isPhase2": false,
        "bonus": {
          "aspectsLieSupplementaire": {
            "has": false,
            "value": "chair"
          },
          "sante": {
            "has": false,
            "aspect": {
              "lie": false,
              "value": "chair",
              "multiplie": 5
            },
            "value": 0
          },
          "armure": {
            "has": false,
            "aspect": {
              "lie": false,
              "value": "chair",
              "multiplie": 5
            },
            "value": 0
          },
          "aspectMax": {
            "has": false,
            "aspect": "chair",
            "maximum": {
              "aspect": 40,
              "ae": 20
            }
          }
        },
        "degats": {
          "has": false,
          "system": {
            "dice": 0,
            "fixe": 0,
            "effets": {
              "raw": [],
              "custom": [],
              "liste": []
            }
          }
        },
        "attaque": {
          "has": false,
          "type": "contact",
          "portee": "contact",
          "degats": {
            "dice": 0,
            "fixe": 0
          },
          "effets": {
            "raw": [],
            "custom": [],
            "liste": []
          }
        },
        "phase2": {
          "aspects": {
            "has": false,
            "liste": {
              "chair": {
                "value": 0
              },
              "bete": {
                "value": 0
              },
              "machine": {
                "value": 0
              },
              "dame": {
                "value": 0
              },
              "masque": {
                "value": 0
              }
            }
          },
          "sante": {
            "has": false,
            "value": 0
          },
          "armure": {
            "has": false,
            "value": 0
          },
          "tactique": {
            "has": false,
            "value": ""
          }
        }
      },
      "effects": [],
      "_id": "d1Xr1vwDuYsb7hRT",
      "ownership": {
        "default": 0
      },
      "flags": {
        "core": {
          "sourceId": "Compendium.knight-compendium.npc-capacities-base.14b5daf85c0b478a"
        }
      },
      "_stats": {
        "systemId": "knight",
        "systemVersion": "1.4.9",
        "coreVersion": "10.288",
        "createdTime": 1666890018810,
        "modifiedTime": 1667213023056,
        "lastModifiedBy": "y7bwecrKsFInhWQ1"
      },
      "folder": "FdIw3AaAAqfstH0n",
      "sort": 0,
      "_key": "!actors.items!Q1Jo0bLeYPUEFL1G.d1Xr1vwDuYsb7hRT"
    }
  ],
  "effects": [],
  "flags": {
    "core": {
      "sourceId": "Compendium.knight-compendium.la-geste-de-la-fin-des-temps-arc-de-la-machine.Q1Jo0bLeYPUEFL1G"
    }
  },
  "_stats": {
    "systemId": "knight",
    "systemVersion": "3.10.2",
    "coreVersion": "10.291",
    "createdTime": 1667212709315,
    "modifiedTime": 1685567372832,
    "lastModifiedBy": "Kisv9JwB5w6zIXyv"
  },
  "_id": "Q1Jo0bLeYPUEFL1G",
  "folder": null,
  "sort": 0,
  "ownership": {
    "default": 0
  },
  "_key": "!actors!Q1Jo0bLeYPUEFL1G"
}
